py_selenium_auto/__init__.py
py_selenium_auto/py.typed
py_selenium_auto/browsers/__init__.py
py_selenium_auto/browsers/browser.py
py_selenium_auto/browsers/browser_services.py
py_selenium_auto/browsers/browser_startup.py
py_selenium_auto/browsers/java_script.py
py_selenium_auto/browsers/browser_factory/__init__.py
py_selenium_auto/browsers/browser_factory/browser_factory.py
py_selenium_auto/browsers/browser_factory/local_browser_factory.py
py_selenium_auto/browsers/browser_navigation/__init__.py
py_selenium_auto/browsers/browser_navigation/browser_navigation.py
py_selenium_auto/browsers/browser_navigation/browser_tab_navigation.py
py_selenium_auto/browsers/enums/__init__.py
py_selenium_auto/browsers/enums/alert_actions.py
py_selenium_auto/configurations/__init__.py
py_selenium_auto/configurations/browser_profile.py
py_selenium_auto/configurations/timeout_configuration.py
py_selenium_auto/configurations/web_driver_settings/__init__.py
py_selenium_auto/configurations/web_driver_settings/chrome_settings.py
py_selenium_auto/configurations/web_driver_settings/driver_settings.py
py_selenium_auto/elements/__init__.py
py_selenium_auto/elements/button.py
py_selenium_auto/elements/check_box.py
py_selenium_auto/elements/checkable_element.py
py_selenium_auto/elements/combo_box.py
py_selenium_auto/elements/element.py
py_selenium_auto/elements/element_factory.py
py_selenium_auto/elements/element_state_provider.py
py_selenium_auto/elements/highlight_state.py
py_selenium_auto/elements/label.py
py_selenium_auto/elements/link.py
py_selenium_auto/elements/radio_button.py
py_selenium_auto/elements/text_box.py
py_selenium_auto/elements/actions/__init__.py
py_selenium_auto/elements/actions/check_box_js_actions.py
py_selenium_auto/elements/actions/combobox_js_actions.py
py_selenium_auto/elements/actions/js_actions.py
py_selenium_auto/elements/actions/mouse_actions.py
py_selenium_auto/forms/__init__.py
py_selenium_auto/forms/form.py
py_selenium_auto/logging/__init__.py
py_selenium_auto-0.4.7.dist-info/LICENSE
py_selenium_auto-0.4.7.dist-info/METADATA
py_selenium_auto-0.4.7.dist-info/WHEEL
py_selenium_auto-0.4.7.dist-info/top_level.txt
py_selenium_auto-0.4.7.dist-info/zip-safe
py_selenium_auto-0.4.7.dist-info/RECORD
