Metadata-Version: 2.1
Name: py-selenium-auto
Version: 0.4.7
Summary: Selenium for Python
Home-page: https://github.com/Polmik/py-selenium-auto
Author: Egor Ryaboshapko
Author-email: mrpolmik@hotmail.com
Maintainer: Egor Ryaboshapko
Maintainer-email: mrpolmik@hotmail.com
License: Apache
Keywords: testing,selenium,driver,test automation
Platform: any
Classifier: Programming Language :: Python
Classifier: Programming Language :: Python :: 3.7
Classifier: Programming Language :: Python :: 3.8
Classifier: Programming Language :: Python :: 3.9
Classifier: Programming Language :: Python :: 3.10
Classifier: Programming Language :: Python :: 3.11
Classifier: Programming Language :: Python :: 3.12
Classifier: Programming Language :: Python :: Implementation :: PyPy
Classifier: Framework :: Pytest
Classifier: Topic :: Software Development
Classifier: Topic :: Software Development :: Libraries
Classifier: Topic :: Software Development :: Libraries :: Python Modules
License-File: LICENSE
Requires-Dist: PyHamcrest==2.1.0
Requires-Dist: pytest==7.4.4
Requires-Dist: allure-pytest==2.13.5
Requires-Dist: webdriver-manager==4.0.2
Requires-Dist: dependency-injector-fork==4.42.1
Requires-Dist: py-selenium-auto-core==0.5.6
Requires-Dist: pytest-xdist==3.5.0
Requires-Dist: selenium==4.11.2; python_version <= "3.7"
Requires-Dist: selenium==4.24.0; python_version > "3.7"
